[
    {
        "index": 0,
        "slug": "full-service-zero-bs",
        "title": "Full-Service, Zero BS",
        "action": "Read more about our services",
        "icon": "wrench"
    },
    {
        "index": 1,
        "slug": "full-service-zero-bs",
        "title": "100% Power Every Hour",
        "action": "Read more about our management style",
        "icon": "comment"
    },
    {
        "index": 2,
        "slug": "full-service-zero-bs",
        "title": "Introducing FAST™ PLM",
        "action": "Read more about our strategic process",
        "icon": "hashtag"
    },
    {
        "index": 3,
        "slug": "full-service-zero-bs",
        "title": "FoxZero™ JIRA Tracker",
        "action": "Read more about our tactical operations",
        "icon": "share-alt"
    },
    {
        "index": 4,
        "slug": "full-service-zero-bs",
        "title": "Perfect Aim™ 100% Warranty",
        "action": "Read more about our project guarantee",
        "icon": "money"
    },
    {
        "index": 5,
        "slug": "full-service-zero-bs",
        "title": "Velocity™ Subscription Plans",
        "action": "Read more about our subscription pricing",
        "icon": "line-chart"
    }
]
